autoclickerPy/__init__.py
autoclickerPy/autoclicker.py
autoclickerPy-0.0.2.3.dist-info/LICENSE
autoclickerPy-0.0.2.3.dist-info/METADATA
autoclickerPy-0.0.2.3.dist-info/WHEEL
autoclickerPy-0.0.2.3.dist-info/top_level.txt
autoclickerPy-0.0.2.3.dist-info/RECORD
