Metadata-Version: 2.1
Name: autoclickerPy
Version: 0.0.2.3
Summary: Simple autoclicker for python
Author: Geo
Author-email: <geocraft31@gamil.com>
Keywords: python,autoclicker
Classifier: Development Status :: 1 - Planning
Classifier: Intended Audience :: Developers
Classifier: Programming Language :: Python :: 3
Classifier: Operating System :: Unix
Classifier: Operating System :: MacOS :: MacOS X
Classifier: Operating System :: Microsoft :: Windows
License-File: LICENSE
Requires-Dist: pynput
Requires-Dist: six
